dloop/__init__.py
dloop/events.py
dloop/exceptions.py
dloop/iter_logic.py
dloop/loop.py
dloop/types.py
dloop/utils.py
dloop-0.1.0.dist-info/LICENSE
dloop-0.1.0.dist-info/METADATA
dloop-0.1.0.dist-info/WHEEL
dloop-0.1.0.dist-info/RECORD
