Metadata-Version: 2.1
Name: dloop
Version: 0.1.0
Summary: lightweight Python library that simplifies deep learning training loops by providing an elegant event-based iteration system
Home-page: https://github.com/eballesteros/dloop
License: MIT
Author: Eduardo Ballesteros
Author-email: eduardo.ballesterosg@outlook.com
Requires-Python: >=3.9,<4.0
Classifier: Intended Audience :: Developers
Classifier: License :: OSI Approved :: MIT License
Classifier: Operating System :: OS Independent
Classifier: Programming Language :: Python :: 3
Classifier: Programming Language :: Python :: 3.9
Classifier: Programming Language :: Python :: 3.10
Classifier: Programming Language :: Python :: 3.11
Classifier: Programming Language :: Python :: 3.12
Classifier: Programming Language :: Python :: 3.13
Classifier: Topic :: Software Development :: Libraries
Requires-Dist: tqdm (>=4.67.1,<5.0.0)
Requires-Dist: typing-extensions (>=4.12.2,<5.0.0)
Project-URL: Repository, https://github.com/eballesteros/dloop
